kep_solver/__init__.py
kep_solver/entities.py
kep_solver/fileio.py
kep_solver/generation.py
kep_solver/graph.py
kep_solver/model.py
kep_solver/programme.py
kep_solver/published_generators.py
kep_solver/py.typed
kep_solver/solving.py
kep_solver-4.0.2.dist-info/licenses/LICENSE
kep_solver-4.0.2.dist-info/METADATA
kep_solver-4.0.2.dist-info/WHEEL
kep_solver-4.0.2.dist-info/top_level.txt
kep_solver-4.0.2.dist-info/RECORD
