Metadata-Version: 2.4
Name: kep_solver
Version: 4.0.2
Summary: A Python package for reading and solving single instances of kidney exchange problems.
Author-email: William Pettersson <william@ewpettersson.se>
License:                     GNU AFFERO GENERAL PUBLIC LICENSE
Project-URL: Homepage, https://gitlab.com/wpettersson/kep_solver
Project-URL: Repository, https://gitlab.com/wpettersson/kep_solver
Project-URL: Documentation, https://kep-solver.readthedocs.io/en/latest/index.html
Project-URL: Changelog, https://gitlab.com/wpettersson/kep_solver/-/blob/main/CHANGELOG.md
Keywords: kidney,kidney exchange,kidney exchange programme
Classifier: Programming Language :: Python :: 3
Classifier: Programming Language :: Python :: 3.10
Classifier: Programming Language :: Python :: 3.11
Classifier: Programming Language :: Python :: 3.12
Classifier: License :: OSI Approved :: GNU General Public License v3 (GPLv3)
Classifier: Development Status :: 4 - Beta
Classifier: Operating System :: OS Independent
Requires-Python: >=3.10
License-File: LICENSE
Requires-Dist: pulp
Requires-Dist: defusedxml
Requires-Dist: pandas
Requires-Dist: ruamel.yaml
Provides-Extra: test
Requires-Dist: pytest; extra == "test"
Requires-Dist: mypy>=0.800; extra == "test"
Requires-Dist: black; extra == "test"
Requires-Dist: pytest-cov; extra == "test"
Requires-Dist: xmldiff; extra == "test"
Requires-Dist: highspy; extra == "test"
Provides-Extra: docs
Requires-Dist: sphinx; extra == "docs"
Requires-Dist: sphinx_rtd_theme>=2.0.0; extra == "docs"
Requires-Dist: sphinx_autodoc_typehints; extra == "docs"
Requires-Dist: myst-parser; extra == "docs"
Dynamic: license-file
